msucom_qbank/__init__.py
msucom_qbank/auth.py
msucom_qbank/data/main_mcq.sql
msucom_qbank/data/main_question.sql
msucom_qbank/data/main_quiz.sql
msucom_qbank/data/main_sqlite_master.sql
msucom_qbank/data/test.db
msucom_qbank/db.py
msucom_qbank/quiz.py
msucom_qbank/schema.sql
msucom_qbank/static/style.css
msucom_qbank/templates/auth/login.html
msucom_qbank/templates/auth/register.html
msucom_qbank/templates/layout.html
msucom_qbank/templates/quiz/add_question.html
msucom_qbank/templates/quiz/exam.html
msucom_qbank/templates/quiz/index.html
msucom_qbank/templates/quiz/question_return.html
msucom_qbank/templates/quiz/quiz.html
msucom_qbank-0.1.0.dist-info/WHEEL
msucom_qbank-0.1.0.dist-info/METADATA
msucom_qbank-0.1.0.dist-info/RECORD
