Metadata-Version: 2.1
Name: msucom-qbank
Version: 0.1.0
Summary: 
License: MIT
Author: BGASM
Author-email: slatte26@msu.edu
Requires-Python: >=3.8,<4.0
Classifier: License :: OSI Approved :: MIT License
Classifier: Programming Language :: Python :: 3
Classifier: Programming Language :: Python :: 3.8
Classifier: Programming Language :: Python :: 3.9
Requires-Dist: Flask (>=1.1.2,<2.0.0)
Requires-Dist: gunicorn (>=20.0.4,<21.0.0)
Requires-Dist: loguru (>=0.5.3,<0.6.0)
